README.md
README.rst
setup.py
django_json_secrets.egg-info/PKG-INFO
django_json_secrets.egg-info/SOURCES.txt
django_json_secrets.egg-info/dependency_links.txt
django_json_secrets.egg-info/top_level.txt
django_json_secrets.egg-info/zip-safe
djs/__init__.py