Metadata-Version: 1.0
Name: django-json-secrets
Version: 0.1.5
Summary: JSON secrets to Django settings module
Home-page: UNKNOWN
Author: lhy
Author-email: dev@lhy.kr
License: MIT
Platform: UNKNOWN
